jjsutils/Game.py
jjsutils-0.0.1.dist-info/METADATA
jjsutils-0.0.1.dist-info/WHEEL
jjsutils-0.0.1.dist-info/top_level.txt
jjsutils-0.0.1.dist-info/RECORD
