Metadata-Version: 2.1
Name: jjsutils
Version: 0.0.1
Summary: util modules by JJS
Home-page: https://github.com/tingstyle1/jjsutils
Author: JJS
Author-email: tingstyle1@gmail.com
License: MIT
Platform: UNKNOWN
Requires-Dist: requests
